FreeSimpleGUIQt/__init__.py
freesimpleguiqt-2.0.0.dist-info/METADATA
freesimpleguiqt-2.0.0.dist-info/NOTICE
freesimpleguiqt-2.0.0.dist-info/WHEEL
freesimpleguiqt-2.0.0.dist-info/top_level.txt
freesimpleguiqt-2.0.0.dist-info/RECORD
